LICENSE
MANIFEST.in
README.rst
setup.py
clean_validator/__init__.py
clean_validator/cli.py
clean_validator.egg-info/PKG-INFO
clean_validator.egg-info/SOURCES.txt
clean_validator.egg-info/dependency_links.txt
clean_validator.egg-info/top_level.txt