Metadata-Version: 1.1
Name: clean-validator
Version: 0.0.5
Summary: Used to validate objects cleanly and simply. Very good for testing implementation. ;)
Home-page: https://github.com/sxslex/clean-validator
Author: SleX
Author-email: sx.slex@gmail.com
License: UNKNOWN
Download-URL: https://github.com/sxslex/clean-validator/archive/v0.0.5.tar.gz
Keywords: validate,object,test,py.test
Platform: UNKNOWN
Classifier: License :: OSI Approved :: GNU General Public License (GPL)
Classifier: Natural Language :: English
Classifier: Operating System :: OS Independent
Classifier: Programming Language :: Python :: 2.6
Classifier: Programming Language :: Python :: 2.7
Classifier: Programming Language :: Python :: 3.3
Classifier: Programming Language :: Python :: 3.4
Classifier: Programming Language :: Python :: 3.5
Classifier: Programming Language :: Python :: 3.6
Classifier: Topic :: Software Development :: Libraries :: Python Modules
